sos_sas/__init__.py
sos_sas/_version.py
sos_sas/kernel.py
sos_sas-0.20.0.dist-info/LICENSE
sos_sas-0.20.0.dist-info/METADATA
sos_sas-0.20.0.dist-info/WHEEL
sos_sas-0.20.0.dist-info/entry_points.txt
sos_sas-0.20.0.dist-info/top_level.txt
sos_sas-0.20.0.dist-info/RECORD
